{
  "user": "Heitor",
  "partner": "Livia",
  "months": 3,
  "topTracks": [
    { "rank": 1, "title": "Preferida", "artist": "KayBlack, Wall Hein", "plays": 56, "preview": "/assets/placeholder-audio/short-beat.mp3" },
    { "rank": 2, "title": "Papoulas", "artist": "Yago Oproprio", "plays": 42, "preview": "/assets/placeholder-audio/short-beat.mp3" },
    { "rank": 3, "title": "Mais Ninguém", "artist": "Banda do Mar", "plays": 31, "preview": "/assets/placeholder-audio/short-beat.mp3" },
    { "rank": 4, "title": "Louis V, Menina Linda", "artist": "Sidoka", "plays": 20, "preview": "/assets/placeholder-audio/short-beat.mp3" },
    { "rank": 5, "title": "Mimo Caro - MC GP", "artist": "MC GP, Yunk Vino, Mc Dena", "plays": 12, "preview": "/assets/placeholder-audio/short-beat.mp3" }
  ]
}
